pythx/__init__.py
pythx/types.py
pythx/api/__init__.py
pythx/api/client.py
pythx/api/handler.py
pythx/middleware/__init__.py
pythx/middleware/analysiscache.py
pythx/middleware/base.py
pythx/middleware/group_data.py
pythx/middleware/property_checking.py
pythx/middleware/toolname.py
tests/__init__.py
tests/common.py
tests/test_api_handler.py
tests/test_client.py
tests/test_client_tool_name_middleware.py
tests/test_group_data_middleware.py
tests/test_nocache_middleware.py
tests/test_property_checking_middleware.py
tests/testdata/analysis-input-request.json
tests/testdata/analysis-input-response.json
tests/testdata/analysis-list-request.json
tests/testdata/analysis-list-response.json
tests/testdata/analysis-status-request.json
tests/testdata/analysis-status-response.json
tests/testdata/analysis-submission-request.json
tests/testdata/analysis-submission-response.json
tests/testdata/auth-login-request.json
tests/testdata/auth-login-response.json
tests/testdata/auth-logout-request.json
tests/testdata/auth-logout-response.json
tests/testdata/auth-refresh-request.json
tests/testdata/auth-refresh-response.json
tests/testdata/detected-issues-request.json
tests/testdata/detected-issues-response.json
tests/testdata/group-creation-request.json
tests/testdata/group-creation-response.json
tests/testdata/group-list-request.json
tests/testdata/group-list-response.json
tests/testdata/group-operation-request.json
tests/testdata/group-operation-response.json
tests/testdata/group-status-request.json
tests/testdata/group-status-response.json
tests/testdata/oas-request.json
tests/testdata/version-request.json
tests/testdata/version-response.json
pythx-1.7.3.dist-info/AUTHORS.rst
pythx-1.7.3.dist-info/LICENSE
pythx-1.7.3.dist-info/METADATA
pythx-1.7.3.dist-info/WHEEL
pythx-1.7.3.dist-info/top_level.txt
pythx-1.7.3.dist-info/RECORD
