Metadata-Version: 2.1
Name: pythx
Version: 1.7.3
Summary: A Python library for the MythX platform
Home-page: https://github.com/dmuhs/pythx
Author: Dominik Muhs
Author-email: dominik.muhs@consensys.net
License: MIT license
Keywords: pythx
Classifier: Development Status :: 4 - Beta
Classifier: License :: OSI Approved :: MIT License
Classifier: Natural Language :: English
Classifier: Intended Audience :: Developers
Classifier: Intended Audience :: Education
Classifier: Intended Audience :: Information Technology
Classifier: Topic :: Security
Classifier: Topic :: Software Development :: Libraries :: Python Modules
Classifier: Topic :: Software Development :: Quality Assurance
Classifier: Topic :: Utilities
Classifier: Typing :: Typed
Classifier: Programming Language :: Python :: 3
Classifier: Programming Language :: Python :: 3.6
Classifier: Programming Language :: Python :: 3.7
Classifier: Programming Language :: Python :: 3.8
Classifier: Programming Language :: Python :: Implementation :: PyPy
Requires-Python: >=3.6,<4
License-File: LICENSE
License-File: AUTHORS.rst
Requires-Dist: python-dateutil (==2.8.1)
Requires-Dist: inflection (==0.5.1)
Requires-Dist: PyJWT (==1.7.1)
Requires-Dist: requests (==2.25.1)
Requires-Dist: mythx-models (==2.2.0)
